{"graph_title":"Incidence of anemia among pregnant women aged 15-49 years,","indicator_name":"Prevalence of anemia among women aged 15-49 years by pregnancy status","indicator_number":"2.2.3","page_content":"","reporting_status":"complete","is_global_indicator":true,"goal_number":"2","target_number":"2.2","target_name":"By 2030, end all forms of malnutrition, including achieving, by 2025, the internationally agreed targets on stunting and wasting in children under 5 years of age, and address the nutritional needs of adolescent girls, pregnant and lactating women and older persons","national_geographical_coverage":"Kazakhstan","comments_limitations":"","computation_calculations":"","computation_definitions":"","indicator_available":"Incidence of anemia among pregnant women aged 15-49 years,","national_indicator_description":"","national_metadata_update_url_text":"2021-02-08: see changes on GitHub","national_metadata_update_url":"https://github.com/kazstat/sdg-data-kazstat/commit/81fb14844c840df26aec7e1d484ed3755b054048","national_data_update_url_text":"2020-12-19: see changes on GitHub","national_data_update_url":"https://github.com/kazstat/sdg-data-kazstat/commit/c3e8d258cf58013b62d1143c90f7d04ddafb0c32","indicator":"2.2.3","target_id":"2.2","sdg_goal":"2","data_non_statistical":false,"graph_type":"line","indicator_sort_order":"02-02-03"}