{"computation_units":"data.\u0442\u044b\u0441.\u0442\u0435\u043d\u0433\u0435","data_non_statistical":false,"data_show_map":true,"graph_title":"Productivity in the agricultural sector","graph_type":"line","indicator_name":"Volume of production per labour unit by classes of farming/pastoral/forestry enterprise size","indicator_number":"2.3.1","page_content":"","reporting_status":"complete","tags":[],"is_global_indicator":true,"goal_number":"2","target_number":"2.3","target_name":"By 2030, double the agricultural productivity and incomes of small-scale food producers, in particular women, indigenous peoples, family farmers, pastoralists and fishers, including through secure and equal access to land, other productive resources and inputs, knowledge, financial services, markets and opportunities for value addition and non-farm employment","national_geographical_coverage":"Kazakhstan","availability":1,"classification":1,"comments_limitations":"","computation_calculations":"","computation_definitions":"","customisation":"Alternative national","goal_meta_link":"https://unstats.un.org/sdgs/files/metadata-compilation/Metadata-Goal-2.pdf","goal_meta_link_text":"United Nations Sustainable Development Goals Metadata (PDF 4.0 MB)","indicator_available":"Productivity in the agricultural sector","national_indicator_description":"","source_active_1":true,"source_compilation_1":"Ministry of National Economy of the Republic of Kazakhstan  Committee on Statistics","source_data_1":"Gross Value Added (GVA) of agriculture, forestry and fisheries at current prices, population","source_implementation_1":"Ministry of Agriculture of the Republic of Kazakhstan","un_custodian_agency":"Food and Agricultural Organization (FAO)","un_designated_tier":"3","national_metadata_update_url_text":"2021-02-08: see changes on GitHub","national_metadata_update_url":"https://github.com/kazstat/sdg-data-kazstat/commit/81fb14844c840df26aec7e1d484ed3755b054048","national_data_update_url_text":"2021-02-02: see changes on GitHub","national_data_update_url":"https://github.com/kazstat/sdg-data-kazstat/commit/5e3be2f733290b0f2587e0c6381c2c88eca5debb","indicator":"2.3.1","target_id":"2.3","sdg_goal":"2","indicator_sort_order":"02-03-01"}