{"Year":[2010,2010,2010,2010,2010,2010,2010,2010,2010,2010,2010,2010,2010,2010,2010,2010,2010,2010,2010,2010,2010,2010,2010,2010,2010,2010,2015,2015,2015,2015,2015,2015,2015,2015,2015,2015,2015,2015,2015,2015,2015,2015,2015,2015,2015,2015,2015,2015,2015,2015,2015,2015],"UNIT_MEASURE":["PT","PT","PT","PT","PT","PT","PT","PT","PT","PT","PT","PT","PT","PT","PT","PT","PT","PT","PT","PT","PT","PT","PT","PT","PT","PT","PT","PT","PT","PT","PT","PT","PT","PT","PT","PT","PT","PT","PT","PT","PT","PT","PT","PT","PT","PT","PT","PT","PT","PT","PT","PT"],"SEX":[null,null,null,"M","F",null,null,null,null,null,null,null,null,null,null,null,null,null,null,null,null,null,null,null,null,null,null,null,null,"M","F",null,null,null,null,null,null,null,null,null,null,null,null,null,null,null,null,null,null,null,null,null],"URBANISATION":[null,"U","R",null,null,null,null,null,null,null,null,null,null,null,null,null,null,null,null,null,null,null,null,null,null,null,null,"U","R",null,null,null,null,null,null,null,null,null,null,null,null,null,null,null,null,null,null,null,null,null,null,null],"AGE":[null,null,null,null,null,"Y0","M12T23","M24T35","M36T47","M48T59",null,null,null,null,null,null,null,null,null,null,null,null,null,null,null,null,null,null,null,null,null,"Y0","M12T23","M24T35","M36T47","M48T59",null,null,null,null,null,null,null,null,null,null,null,null,null,null,null,null],"REF_AREA":[null,null,null,null,null,null,null,null,null,null,"KZAKM","KZAKT","KZALM","KZATY","KZZAP","KZZHA","KZKAR","KZKUS","KZKZY","KZMAN","KZONT","KZPAV","KZSEV","KZVOS","KZNS","KZALA",null,null,null,null,null,null,null,null,null,null,"KZAKM","KZAKT","KZALM","KZATY","KZZAP","KZZHA","KZKAR","KZKUS","KZKZY","KZMAN","KZONT","KZPAV","KZSEV","KZVOS","KZNS","KZALA"],"Value":[99.7,99.9,99.6,99.8,99.7,99.1,99.9,99.9,99.9,100.0,98.8,99.6,100.0,99.7,100.0,99.7,99.8,98.7,100.0,99.7,100.0,99.6,98.8,99.6,100.0,100.0,99.7,99.9,99.5,99.7,99.7,98.7,100.0,100.0,99.8,100.0,100.0,100.0,99.1,98.9,99.7,99.4,99.6,100.0,99.5,99.8,99.8,100.0,99.5,100.0,99.7,100.0]}